{"result": 100, "data": {"retcode": 0, "code": 0, "subcode": 0, "lyric": "[ti:遗书]\n[ar:蔡健雅]\n[al:遗书]\n[by:]\n[offset:0]\n[00:00.00]遗书 - 蔡健雅 (Tanya Chua)\n[00:07.69]词：葛大为/蔡健雅\n[00:15.39]曲：蔡健雅\n[00:23.09]平常不过的 夜晚\n[00:28.39]这是我最后一次\n[00:31.42]给自己交代\n[00:34.16]确定没留下任何遗憾\n[00:39.47]没有任何的不安\n[00:42.50]跟未知对谈\n[00:49.15]我曾爱过的 ooh 都爱过了\n[00:54.68]曾看不开的 或许不一定都要释怀\n[01:00.26]我也认真过了 付出多过获得\n[01:05.52]但愿他们记得 感动的每一刻\n[01:16.56]把留下的泪水 藏不住的心碎\n[01:22.73]写成歌给人安慰\n[01:27.70]我闭上眼睛唱着 感谢这一生\n[01:34.07]没白费\n[01:51.73]世界会照样 运转\n[01:57.10]只是我已出发在\n[02:00.14]旅程另一段\n[02:02.97]走在人群中特别孤单\n[02:08.17]这个错误的安排\n[02:11.23]不需要重来\n[02:17.86]我曾爱过的 ooh 都爱过了\n[02:22.94]曾看不开的 或许不一定都要释怀\n[02:28.51]我也认真过了 付出多过获得\n[02:33.89]但愿他们记得 感动的每一刻\n[02:44.76]把留下的泪水 藏不住的心碎\n[02:51.03]写成歌给人安慰\n[02:56.11]我闭上眼睛唱着 感谢这一生\n[03:02.31]没白费\n[03:07.58]我会留下什么\n[03:11.00]请替我保管\n[03:13.40]就别不舍得\n[03:15.16]Ooh we&apos;re gonna make it through\n[03:18.97]我是被疼爱的\n[03:22.11]我会好好的\n[03:24.21]得到你的祝福\n[03:29.59]怎么会不想哭\n[03:35.60]我会去片大海\n[03:37.93]无忧无虑去爱\n[03:41.32]像尘埃 自由 自在\n[03:46.16]在那一片大海\n[03:49.02]告别了感慨\n[03:52.56]So goodnight\n[03:58.01]Goodbye", "trans": ""}}