{"result": 100, "data": {"retcode": 0, "code": 0, "subcode": 0, "lyric": "[ti:我很好 (吉他版)]\n[ar:刘大壮]\n[al:我很好]\n[by:]\n[offset:0]\n[00:00.00]我很好 (吉他版) - 刘大壮\n[00:00.90]词：刘家泽/晨晨晨\n[00:01.81]曲：晨晨晨\n[00:02.72]吉他：刘大壮\n[00:03.63]音频编辑：任天宇\n[00:04.54]宣发：李永江/小阮/游文雅\n[00:05.45]制作人：苏晨\n[00:06.36]监制：刘家泽/苏晨/游文雅\n[00:07.27]统筹：徐阳/李文景/冯昌榆\n[00:08.18]制作公司：匠心音乐\n[00:09.09]发行：蔚来音乐 V-LAND Music\n[00:09.99]出品：「匠心娱乐」x 「造音行动」\n[00:10.91]还记得属于你的那些嗜好\n[00:15.50]喜欢吃的菜系和饮料\n[00:19.45]习惯的动作 连带着微笑\n[00:24.21]在最远的星空闪耀\n[00:27.98]还记得爱你时的每个心跳\n[00:32.26]还保留着每一张合照\n[00:36.68]可能是矫情 庸人被自扰\n[00:41.13]这么多年哪舍得删掉\n[00:45.55]经历过天堂般的美好\n[00:49.68]又怎舍得在地狱煎熬\n[00:53.84]是不甘心的 自私再叨扰\n[00:57.86]还是真的爱你 无可救药\n[01:03.39]我很好\n[01:04.74]只是偶尔遗憾会从眼里掉\n[01:08.14]我很好\n[01:08.95]怎么拼命忘却还是忘不掉\n[01:12.21]丢失的那份美好\n[01:15.03]在疲惫中睡着\n[01:20.21]我很好\n[01:21.43]反正一直都是偶尔被需要\n[01:24.96]我很好\n[01:25.82]就算再冷我也只相信外套\n[01:29.18]答应你的\n[01:30.64]我能把自己照顾好\n[01:49.28]还记得爱你时的每个心跳\n[01:53.06]还保留着每一张合照\n[01:57.42]可能是矫情 庸人被自扰\n[02:01.67]这么多年哪舍得删掉\n[02:05.60]经历过天堂般的美好\n[02:09.95]又怎舍得在地狱煎熬\n[02:13.87]是不甘心的 自私再叨扰\n[02:17.94]还是真的爱你 无可救药\n[02:24.35]我很好\n[02:25.52]只是偶尔遗憾会从眼里掉\n[02:28.88]我很好\n[02:29.72]怎么拼命忘却还是忘不掉\n[02:32.93]丢失的那份美好\n[02:35.39]在疲惫中睡着\n[02:40.39]我很好\n[02:41.64]反正一直都是偶尔被需要\n[02:45.00]我很好\n[02:45.82]就算再冷我也只相信外套\n[02:49.03]答应你的\n[02:50.25]我能把自己照顾好\n[02:56.51]我很好\n[02:57.68]只是偶尔遗憾会从眼里掉\n[03:00.94]我很好\n[03:01.86]怎么拼命忘却还是忘不掉\n[03:05.03]丢失的那份美好\n[03:07.57]在疲惫中睡着\n[03:12.48]我很好\n[03:13.72]反正一直都是偶尔被需要\n[03:17.05]我很好\n[03:17.92]就算再冷我也只相信外套\n[03:21.11]答应你的\n[03:22.38]我能把自己照顾好\n[03:28.51]答应你的\n[03:29.53]我能把自己照顾好", "trans": ""}}