{"result": 100, "data": {"retcode": 0, "code": 0, "subcode": 0, "lyric": "[ti:Let It Snow! Let It Snow! Let It Snow!b]\n[ar:Dean Martin]\n[al:Little Donkey]\n[by:]\n[offset:0]\n[00:00.00]Let It Snow! Let It Snow! Let It Snow!b - Dean Martin (迪安·马丁)\n[00:04.47]Lyrics by：Dean Martin\n[00:08.95]Composed by：Dean Martin\n[00:13.43]Oh the weather outside is frightful\n[00:16.67]But the fire is so delightful\n[00:20.21]And since we&apos;ve no place to go\n[00:23.69]Let it snow let it snow let it snow\n[00:27.33]Man it doesn&apos;t show signs of stopping\n[00:30.73]And I&apos;ve brought me some corn for popping\n[00:34.66]The lights are turned way down low\n[00:37.91]Let it snow let it snow\n[00:41.73]When we finally kiss goodnight\n[00:45.00]How I&apos;ll hate going out in the storm\n[00:48.67]But if you really hold me tight\n[00:52.58]All the way home I&apos;ll be warm\n[00:55.78]And the fire is slowly dying\n[00:59.35]And my dear we&apos;re still goodbying\n[01:02.86]But as long as you love me so\n[01:06.22]Let it snow let it snow and snow\n[01:24.53]When we finally kiss goodnight\n[01:27.75]How I&apos;ll hate going out in the storm\n[01:31.33]But if you really grab me tight\n[01:35.15]All the way home I&apos;ll be warm\n[01:38.20]Oh the fire is slowly dying\n[01:41.93]And my dear we&apos;re still goodbying\n[01:45.29]But as long as you love me so\n[01:48.82]Let it snow let it snow let it snow", "trans": "[ti:Let It Snow! Let It Snow! Let It Snow!b]\n[ar:Dean Martin]\n[al:Little Donkey]\n[by:]\n[offset:0]\n[00:00.00]以下歌词翻译由微信翻译提供\n[00:04.47]//\n[00:08.95]//\n[00:13.43]外面的天气糟糕透顶\n[00:16.67]但烈火如此令人愉悦\n[00:20.21]因为我们无处可去\n[00:23.69]让雪下起来\n[00:27.33]朋友这一切没有停止的迹象\n[00:30.73]我带了一些玉米来给自己做点好东西\n[00:34.66]灯光调暗一点\n[00:37.91]让雪下起来\n[00:41.73]当我们终于互道晚安\n[00:45.00]我多么讨厌在狂风暴雨中出门\n[00:48.67]但如果你真的紧紧抱着我\n[00:52.58]一路回家我会感到温暖\n[00:55.78]火焰慢慢熄灭\n[00:59.35]亲爱的我们依然在道别\n[01:02.86]但只要你真心爱我\n[01:06.22]让雪下起来让雪越下越大\n[01:24.53]当我们终于互道晚安\n[01:27.75]我多么讨厌在狂风暴雨中出门\n[01:31.33]但如果你真的紧紧地抱着我\n[01:35.15]一路回家我会感到温暖\n[01:38.20]爱火慢慢熄灭\n[01:41.93]亲爱的我们依然在道别\n[01:45.29]但只要你真心爱我\n[01:48.82]让雪下起来\n"}}