{"result": 100, "data": {"retcode": 0, "code": 0, "subcode": 0, "lyric": "[ti:WHAT&apos;S GOOD (Explicit)]\n[ar:Tyler, The Creator]\n[al:IGOR (Explicit)]\n[by:]\n[offset:0]\n[00:00.00]WHAT'S GOOD (Explicit) - Tyler, The Creator\n[00:03.09]Lyrics by：Tyler Okonma\n[00:06.18]Composed by：Tyler Okonma\n[00:09.27]Turn my lights on\n[00:10.42]How the f**k you quiet with the mic on\n[00:12.33]I don&apos;t get anxiety you Sam Bowie-ass n***as\n[00:14.78]I just get my Mike on\n[00:16.23]Y&apos;all said I wouldn&apos;t go nowhere took the detour\n[00:18.56]When you see the someone in the crack right by the sea shore\n[00:20.62]When you see them brand new le Fleurs on the floor\n[00:22.65]If the cop says my name b***h I&apos;m Igor\n[00:26.59]Yuh ayo\n[00:30.56]Yeah yeah\n[00:32.39]Let&apos;s go let&apos;s go I ain&apos;t playin&apos; around\n[00:34.54]Red nose red nose all you n***as is clowns\n[00:36.59]N***as turning it up well shit I&apos;m tearing it down\n[00:38.46]Hard to believe in God when there ain&apos;t no mirrors around\n[00:40.38]What&apos;s up\n[00:42.65]Uh-huh ayo\n[00:46.79]Uh-huh\n[00:48.84]Yeah yo\n[00:52.97]B***h\n[00:53.49]Running &apos;til the rims fall\n[00:54.60]Had them n***as and the cops looking jigsaw\n[00:56.87]I done f**ked around and turned into the big dog\n[00:58.69]Better get gone get caught b***h I think not\n[01:00.81]Yeah new suit new boots same n***as like what\n[01:03.41]Lukewarm-ass n***as always wanna talk\n[01:05.90]I&apos;m hot I&apos;m heat to the core like Earth\n[01:07.51]Don&apos;t touch don&apos;t go n***as might get bucked\n[01:11.39]Yo yuh ayo\n[01:16.93]Yeah\n[01:17.33]Let&apos;s go let&apos;s go I ain&apos;t playin&apos; around\n[01:19.43]Red nose red nose all you n***as is clowns\n[01:21.48]N***as turning it up well s**t I&apos;m tearing it down\n[01:23.18]Hard to believe in God when there ain&apos;t no mirrors around\n[01:25.36]What&apos;s up\n[01:27.56]Whoop uh huh\n[01:31.61]Yeah b***h\n[01:41.65]I see the light\n[01:42.71]Now didn&apos;t I tell you motherf**kers\n[01:44.60]Um I see the light\n[01:46.33]To pay attention and to keep your motherf**king eyes\n[01:49.05]Glued to the man that&apos;s in front of you\n[01:50.48]I see the light\n[01:51.12]That&apos;s what the f**k I expect all y&apos;all motherf**kers to do\n[01:53.32]I see the light\n[01:54.43]Dracula Dracula Dracula\n[01:56.62]Suck me first I might get back at ya\n[01:58.02]I see the light\n[01:58.75]Is that shit cool Change the aperture\n[02:00.16]Hahahahaha I can&apos;t laugh at ya\n[02:01.98]I see the light\n[02:02.59]This the s**t that make you nervous\n[02:04.41]&apos;Bout to go buck wild n***a Steve Irwin\n[02:05.92]I see the light\n[02:06.59]Sick of that Claritin I&apos;m on my third one\n[02:08.16]N***as talkin&apos; reckless I never heard &apos;em\n[02:09.66]I see the light\n[02:14.10]I see the light\n[02:18.10]I see the light\n[02:18.85]F**ked up touched up my n***as might get f**ked up touched up\n[02:22.07]I see the light\n[02:23.12]F**ked up touched up my n***as might get f**ked up touched up\n[02:26.20]I see the light\n[02:27.28]That car crash couldn&apos;t take me\n[02:28.64]Woo ha\n[02:29.13]Green hair angels all around me\n[02:30.61]Uh\n[02:31.11]No answer why no tears to cry b***h I&apos;m alive\n[02:33.87]I see the\n[02:35.25]This wasn&apos;t my endpoint like v-neck\n[02:37.05]I ain&apos;t have nobody to cheat on I cheat death\n[02:39.15]New album no repeat I reset\n[02:41.00]Everything I deliver swingin&apos; like new jack\n[02:42.83]Two of &apos;em I total Kim and Pam\n[02:45.32]Me and Death universe plays middle man\n[02:47.28]Quit nap kick back my eyes closed shut\n[02:49.38]Loud sound no stretch\n[02:50.37]Motherf**kers really thought I died\n[02:52.28]Hoping they could take a spot\n[02:53.42]N***a not knowing that I&apos;m one of one\n[02:55.38]And they some Helen Keller-ass n***as\n[02:56.89]And I got my eyes open now I see the light\n[03:03.05]I see the light\n[03:03.98]You never wanna meet a motherf**ker like me\n[03:06.94]I see the light\n[03:07.59]I said\n[03:11.12]I see the light\n[03:15.17]I see the light\n[03:22.46]I don&apos;t know what&apos;s harder letting go or just being okay with it", "trans": "[ti:WHAT'S GOOD (Explicit)]\n[ar:Tyler, The Creator]\n[al:IGOR (Explicit)]\n[by:]\n[offset:0]\n[00:00.00]//\n[00:03.09]//\n[00:06.18]//\n[00:09.27]舞台灯光亮起\n[00:10.42]麦克风已经开启 你怎么还一言不发\n[00:12.33]我没有得焦虑症 你们就像球员Sam Bowie一样伤病缠身\n[00:14.78]我拿起麦克风\n[00:16.23]你们都说我会一事无成 但我另辟蹊径\n[00:18.56]你见过哪个穷人会去海边度假吗\n[00:20.62]你见过谁穿着Golf le Fleurs的鞋子踩在地上吗\n[00:22.65]警察喊我的名字 我头也不回\n[00:26.59]//\n[00:30.56]//\n[00:32.39]走吧 走吧 我不喜欢四处招摇\n[00:34.54]你们都是涂着红鼻子的小丑\n[00:36.59]你们的音乐只是小打小闹 而我的音乐震耳欲聋\n[00:38.46]我只相信镜子里的我 我才是真正的上帝\n[00:40.38]怎么了\n[00:42.65]//\n[00:46.79]//\n[00:48.84]//\n[00:52.97]碧池\n[00:53.49]一路飞驰 直到车子报废\n[00:54.60]我的对手们和那些警察都很困惑 他们摸不清我的套路\n[00:56.87]我四处奔忙 成为了音乐界的大人物\n[00:58.69]你叫我快点跑 别被抓了 碧池 这不可能\n[01:00.81]穿着新衣服 新鞋子 但我还是原来的我\n[01:03.41]那些从前对我冷淡的人现在又想和我搭讪\n[01:05.90]我现在火了 火遍全世界\n[01:07.51]别碰我 别轻举妄动 小心我揍你\n[01:11.39]//\n[01:16.93]//\n[01:17.33]走吧 走吧 我不喜欢四处招摇\n[01:19.43]你们都是涂着红鼻子的小丑\n[01:21.48]你们的音乐只是小打小闹 而我的音乐震耳欲聋\n[01:23.18]我只相信镜子里的我 我才是真正的上帝\n[01:25.36]怎么了\n[01:27.56]//\n[01:31.61]碧池\n[01:41.65]我看见了希望\n[01:42.71]我没跟你说吗 小子\n[01:44.60]我看见了希望\n[01:46.33]都给我集中注意 眼珠子别乱动\n[01:49.05]盯紧你眼前这个人\n[01:50.48]我看见了希望\n[01:51.12]我希望你们都能按我说的做\n[01:53.32]我看见了希望\n[01:54.43]吸血鬼Count Dracula\n[01:56.62]是你先吸了我的血 我会报仇的\n[01:58.02]我看见了希望\n[01:58.75]这样酷吗 睁开眼睛\n[02:00.16]我不能嘲笑你\n[02:01.98]我看见了希望\n[02:02.59]这才是让你紧张的原因吧\n[02:04.41]我要彻底变得疯狂了\n[02:05.92]我看见了希望\n[02:06.59]讨厌吃过敏药 我已经吃了三次了\n[02:08.16]那些人说话不过脑子 我从来不放在心上\n[02:09.66]我看见了希望\n[02:14.10]我看见了希望\n[02:18.10]我看见了希望\n[02:18.85]别乱动 否则休怪我对你不客气\n[02:22.07]我看见了希望\n[02:23.12]别乱动 否则休怪我对你不客气\n[02:26.20]我看见了希望\n[02:27.28]一场车祸不可能要了我的命\n[02:28.64]//\n[02:29.13]天使一直庇佑着我\n[02:30.61]//\n[02:31.11]不想解释太多 我不会流泪 碧池 我还活着\n[02:33.87]我看见\n[02:35.25]我的人生不会就此终结\n[02:37.05]我不会欺骗任何人 我和死神捉迷藏\n[02:39.15]新专辑 没有重制的歌曲 我从头开始\n[02:41.00]我的每一个作品都是受人欢迎的佳作\n[02:42.83]我的实力一个顶俩 堪比Total组合的Kima Dyson和Pam Long\n[02:45.32]我和死神中间隔了一个宇宙\n[02:47.28]别再打盹了 我闭着眼睛也能收拾你们\n[02:49.38]声音大雨点小\n[02:50.37]他们还以为我真的死了\n[02:52.28]希望他们不会输得太惨\n[02:53.42]他们不知道 我是独一无二的\n[02:55.38]他们对眼前的机会视而不见\n[02:56.89]而我睁大双眼 我看见了希望\n[03:03.05]我看见了希望\n[03:03.98]你们都不想碰到我这样的高手\n[03:06.94]我看见了希望\n[03:07.59]我说\n[03:11.12]我看见了希望\n[03:15.17]我看见了希望\n[03:22.46]我不知道放手和接受哪个更难"}}