{"result": 100, "data": {"retcode": 0, "code": 0, "subcode": 0, "lyric": "[ti:落海]\r\n[ar:任然]\r\n[al:落海]\r\n[by:]\r\n[offset:0]\r\n[00:01.41]落海 - 任然\r\n[00:02.30]词：耕耕\r\n[00:02.98]曲：Kent王健\r\n[00:03.81]制作人：Kent王健\r\n[00:04.92]编曲：杨云翔\r\n[00:05.86]吉他/贝斯：杨云翔\r\n[00:06.09]弦乐编写：杨云翔\r\n[00:06.87]弦乐：国际首席爱乐乐团\r\n[00:07.20]弦乐监制：李朋\r\n[00:07.40]混音/母带：张栩赫（Ethan）\r\n[00:07.66]录音：Kent王健\r\n[00:07.83]和声编写/和声：Kent王健\r\n[00:08.13]配唱制作人：Kent王健\r\n[00:08.39]人声录音工作室：XXL Studio\r\n[00:08.69]混音/母带工作室：XXL Studio\r\n[00:09.58]弦乐录音工作室：2496 Top Music Studio\r\n[00:09.94]监制：三千\r\n[00:10.07]OP：千和世纪\r\n[00:10.23]（版权所有未经许可请勿使用）\r\n[00:22.66]微光潮汐繁华千寻在深海中潜行\r\n[00:28.90]我唱吟\r\n[00:30.66]蔚蓝色寰宇赋予我的回应多冷清\r\n[00:38.81]孤单频率万籁寂静在时间里旅行\r\n[00:45.41]我迁徙 这海域\r\n[00:47.40]继续前行我独一无二的轨迹\r\n[00:53.44]我等你靠近等来海啸入侵\r\n[00:57.61]想听你声音听见风暴奔袭\r\n[01:01.85]孑然的心 伟岸的生命\r\n[01:05.84]倔强呐喊着叹息\r\n[01:09.58]我是没遇见你就落入海底的鲸\r\n[01:14.59]你若途经却听不见我呼吸\r\n[01:18.27]辗转的梦境 我昂首去证明\r\n[01:22.16]就算一生孤寂 共鸣一样清晰\r\n[01:26.57]不是你的风景只是海底的鲸\r\n[01:30.65]提醒我在你眼里只能透明\r\n[01:34.54]你有万物生灵\r\n[01:36.73]我是最渺小的倒影\r\n[02:02.75]我等你靠近等来海啸入侵\r\n[02:06.82]想听你声音听见风暴奔袭\r\n[02:11.25]孑然的心 伟岸的生命\r\n[02:15.08]倔强呐喊着叹息\r\n[02:18.59]我是没遇见你就落入海底的鲸\r\n[02:23.59]你若途经却听不见我呼吸\r\n[02:27.56]辗转的梦境 我昂首去证明\r\n[02:31.37]就算一生孤寂 共鸣一样清晰\r\n[02:35.75]不是你的风景只是海底的鲸\r\n[02:40.00]提醒我在你眼里只能透明\r\n[02:43.64]你有万物生灵\r\n[02:45.53]我是最渺小的倒影\r\n[03:04.32]没遇见你就落入海底的鲸\r\n[03:08.38]你若途经却听不见我呼吸\r\n[03:12.22]辗转的梦境 我昂首去证明\r\n[03:16.08]就算一生孤寂 共鸣一样清晰\r\n[03:20.45]不是你的风景只是海底的鲸\r\n[03:24.62]提醒我在你眼里只能透明\r\n[03:30.22]你有万物生灵\r\n[03:32.18]我是最渺小的倒影", "trans": ""}}