{"result": 100, "data": {"retcode": 0, "code": 0, "subcode": 0, "lyric": "[ti:Lose Somebody]\n[ar:Kygo/OneRepublic]\n[al:Lose Somebody]\n[by:]\n[offset:0]\n[00:00.00]Lose Somebody - Kygo (凯戈)/OneRepublic (共和时代)\n[00:04.95]Lyrics by：Kyrre Gørvell-Dahll/Ryan Tedder\n[00:09.91]Composed by：Kyrre Gørvell-Dahll/Ryan Tedder\n[00:14.86]It&apos;s a classic &quot;me&quot; mistake\n[00:16.66]Someone gives me love\n[00:18.05]And I throw it all away\n[00:21.16]Tell me have I gone insane\n[00:23.10]Talkin&apos; to myself but I don&apos;t know what to say\n[00:26.08]&apos;Cause you let go\n[00:28.65]And now I&apos;m holdin&apos; on\n[00:31.96]I guess you don&apos;t know what you got\n[00:35.08]Until it&apos;s gone\n[00:39.52]Sometimes you gotta lose somebody\n[00:42.91]Just to find out you really love someone\n[00:45.87]Oh-oh and I do and I do and I do yeah\n[00:52.48]Sometimes you gotta lose somebody\n[00:55.82]Just to find out you really love someone\n[00:58.96]Oh-oh yeah yeah\n[01:02.61]Sometimes you gotta lose somebody\n[01:06.40]So don&apos;t tell me it&apos;s too late\n[01:08.37]Hearts are made to bend\n[01:09.75]Baby please don&apos;t let me break yeah\n[01:13.24]I knew I should&apos;ve stayed\n[01:14.82]&apos;Cause now you&apos;re movin&apos; on\n[01:16.33]And I don&apos;t know what to say\n[01:17.84]&apos;Cause you let go\n[01:19.83]Yeah you let go\n[01:20.89]And now I&apos;m holdin&apos; on I&apos;m holdin&apos; on\n[01:24.22]I guess you don&apos;t know what you got\n[01:26.98]Until it&apos;s gone\n[01:31.46]Sometimes you gotta lose somebody\n[01:34.80]Just to find out you really love someone\n[01:38.14]Oh-oh and I do and I do and I do yeah\n[01:44.41]Sometimes you gotta lose somebody\n[01:47.75]Just to find out you really love someone\n[01:50.76]Oh-oh yeah yeah\n[01:54.41]Sometimes you gotta lose somebody\n[02:00.82]Sometimes you gotta lose somebody yeah\n[02:07.15]Sometimes you gotta lose somebody yeah\n[02:13.66]Sometimes you gotta lose somebody yeah\n[02:20.22]Sometimes you gotta lose somebody yeah\n[02:23.37]Sometimes you gotta lose somebody\n[02:26.79]Just to find out you really love someone\n[02:29.71]Oh-oh and I do and I do and I do yeah\n[02:36.27]Sometimes you gotta lose somebody\n[02:39.65]Just to find out you really love someone\n[02:42.67]Oh-oh yeah yeah\n[02:46.01]Sometimes you gotta lose somebody\n[02:49.10]Ooh\n[03:11.62]Sometimes you gotta lose some\n[03:12.85]You gotta lose somebody", "trans": "[ti:Lose Somebody]\n[ar:Kygo/OneRepublic]\n[al:Lose Somebody]\n[by:]\n[offset:0]\n[00:00.00]腾讯享有本翻译作品的著作权\n[00:04.95]//\n[00:09.90]//\n[00:14.86]这是经典的追悔莫及\n[00:16.66]曾有人为我付出真心\n[00:18.05]但我却弃如敝履\n[00:21.16]告诉我 我是不是无可救药\n[00:23.10]自说自话 又苦涩得无从说起\n[00:26.08]因为你已选择放手\n[00:28.65]而我却仍难以释怀\n[00:31.96]我想人只有失去了\n[00:35.08]才会懂得珍惜吧\n[00:39.52]有时候你只有失去了某人\n[00:42.91]才会意识到谁是今生挚爱\n[00:45.87]这就是我的切身体会\n[00:52.48]有时候你只有失去了某人\n[00:55.82]才会意识到谁是今生挚爱\n[00:58.96]//\n[01:02.61]有时候你只有失去了某人\n[01:06.40]拜托 别对我说为时已晚\n[01:08.37]人非草木 孰能无情\n[01:09.75]宝贝 请不要让我伤心欲绝\n[01:13.24]我才悔悟我当初就不该离你而去\n[01:14.82]因为如今你已放下过往\n[01:16.33]徒留无话可说的我\n[01:17.84]因为你已选择放手\n[01:19.83]你已选择放手\n[01:20.89]而我却难以释怀\n[01:24.22]我想人只有失去了\n[01:26.98]才会懂得珍惜吧\n[01:31.46]有时候你只有失去了某人\n[01:34.80]才会意识到谁是今生挚爱\n[01:38.14]这就是我的切身体会\n[01:44.41]有时候你只有失去了某人\n[01:47.75]才会意识到谁是今生挚爱\n[01:50.76]//\n[01:54.41]有时候你只有失去了某人\n[02:00.82]有时候你只有失去了某人\n[02:07.15]有时候你只有失去了某人\n[02:13.66]有时候你只有失去了某人\n[02:20.22]有时候你只有失去了某人\n[02:23.37]有时候你只有失去了某人\n[02:26.79]才会意识到谁是今生挚爱\n[02:29.71]这就是我的切身体会\n[02:36.27]有时候你只有失去了某人\n[02:39.65]才会意识到谁是今生挚爱\n[02:42.67]//\n[02:46.01]有时候你只有失去了某人\n[02:49.10]//\n[03:11.62]有时候你只有失去了某人\n[03:12.85]你只有失去了某人"}}