{"result": 100, "data": {"retcode": 0, "code": 0, "subcode": 0, "lyric": "[ti:亲爱的你 去了何方]\n[ar:陈硕子]\n[al:亲爱的你 去了何方]\n[by:]\n[offset:0]\n[00:00.00]亲爱的你 去了何方 - 陈硕子\n[00:00.15]词：陈硕子\n[00:00.31]曲：陈硕子\n[00:00.46]编曲：王白\n[00:00.62]贝斯：张大雷\n[00:00.77]电吉他：王岳博\n[00:00.93]木吉他：王白\n[00:01.08]混音：十三\n[00:01.24]录音棚：TBE studio\n[00:01.39]混音工作室：柒音乐录音棚/良音文化\n[00:01.55]出品：陈硕子工作室\n[00:01.71]我们都曾在爱情里\n[00:04.09]受过一点伤\n[00:06.04]都曾深爱过对方\n[00:09.61]如今没能让你变成我的新娘\n[00:13.99]亲爱的你去了何方\n[00:37.19]你是我年少时的欢喜\n[00:41.45]是我青春的记忆\n[00:45.39]是我难以忘记\n[00:47.42]是我不愿提及的过去\n[00:53.44]那颗曾为你揉碎的心\n[00:57.41]即使岁月也无法抚平\n[01:01.40]时光荏苒\n[01:03.47]你依然还在我心里\n[01:09.44]我们都曾在爱情里\n[01:11.96]受过一点伤\n[01:13.71]都曾深爱过对方\n[01:17.42]如今没能让你变成我的新娘\n[01:21.88]亲爱的你去了何方\n[01:25.43]我们当初就不应该故意逞强\n[01:29.81]说那些伤人的话\n[01:33.42]如今没能让你变成我的新娘\n[01:37.98]亲爱的你去了何方\n[01:59.45]那颗曾为你揉碎的心\n[02:03.39]即使岁月也无法抚平\n[02:07.26]时光荏苒\n[02:09.69]你依然还在我心里\n[02:15.43]我们都曾在爱情里\n[02:17.98]受过一点伤\n[02:19.77]都曾深爱过对方\n[02:23.45]如今没能让你变成我的新娘\n[02:27.92]亲爱的你去了何方\n[02:31.45]我们当初就不应该故意逞强\n[02:35.91]说那些伤人的话\n[02:39.43]如今没能让你变成我的新娘\n[02:43.90]亲爱的你去了远方\n[02:47.36]我们都曾在爱情里\n[02:49.95]受过一点伤\n[02:51.97]都曾深爱过对方\n[02:55.46]如今没能让你变成我的新娘\n[02:59.94]亲爱的你去了何方\n[03:03.46]我们当初就不应该故意逞强\n[03:07.85]说那些伤人的话\n[03:11.53]如今没能让你变成我的新娘\n[03:15.94]亲爱的你去了何方", "trans": ""}}