{"result": 100, "data": {"retcode": 0, "code": 0, "subcode": 0, "lyric": "[ti:How Do I Make You Love Me?]\n[ar:The Weeknd]\n[al:Dawn FM (Explicit)]\n[by:]\n[offset:0]\n[00:00.00]How Do I Make You Love Me? - The Weeknd\n[00:02.59]Lyrics by：Max Martin/Oscar Holter/Matt Cohn/Abel Tesfaye/Daniel Lopatin/Axel Hedfors/Steve Angello/Sebastian Ingrosso\n[00:05.19]Composed by：Max Martin/Oscar Holter/Matt Cohn/Abel Tesfaye/Daniel Lopatin/Axel Hedfors/Steve Angello/Sebastian Ingrosso\n[00:07.79]We're going back in time\n[00:09.71]I'd like to see you try\n[00:11.73]Unpacking thoughts through tunnels in your mind\n[00:14.44]\n[00:15.59]I'll fix you mushroom tea\n[00:17.64]And cross the restless sea\n[00:19.63]Release yourself to escape reality\n[00:22.48]\n[00:23.57]It doesn't phase you\n[00:25.59]I need a breakthrough\n[00:27.59]I only want what's right in front of me\n[00:30.44]\n[00:31.53]It's quite unusual\n[00:33.51]Seeking approval\n[00:35.53]Begging for it desperately\n[00:38.50]I said\n[00:39.15]\n[00:55.70]How do I make you love me\n[00:58.52]\n[01:00.01]How do I make you fall for me\n[01:02.86]\n[01:03.46]How do I make you want me\n[01:06.57]\n[01:07.71]And make it last eternally\n[01:10.74]\n[01:11.43]How do I make you love me\n[01:14.43]Oh ah\n[01:15.76]How do I make you fall for me\n[01:18.66]\n[01:19.41]How do I make you want me\n[01:22.68]Oh ah\n[01:23.67]And make it last eternally\n[01:27.35]I can see the real you girl\n[01:29.34]You don't have to hide\n[01:31.10]Forget 'bout what your daddy said\n[01:33.00]I'll teach you how to shine\n[01:35.07]And all the things you tolerated\n[01:37.23]Made you cold inside\n[01:38.95]But I can light you up again\n[01:40.86]Like embers of a fire\n[01:42.94]It doesn't phase you\n[01:44.92]I need a breakthrough\n[01:46.89]I only want what's right in front of me\n[01:49.80]\n[01:50.91]It's quite unusual\n[01:52.85]Seeking approval\n[01:54.94]Begging for it desperately\n[01:57.89]I said\n[01:58.56]\n[01:59.18]How do I make you love me\n[02:02.01]\n[02:03.40]How do I make you fall for me\n[02:06.27]\n[02:07.03]How do I make you want me\n[02:10.17]\n[02:11.17]And make it last eternally\n[02:14.22]\n[02:14.90]How do I make you love me\n[02:17.88]Oh ah\n[02:19.19]How do I make you fall for me\n[02:22.16]\n[02:22.97]How do I make you want me\n[02:26.06]Oh ah\n[02:27.18]And make it last eternally\n", "trans": "[ti:How Do I Make You Love Me?]\n[ar:The Weeknd]\n[al:Dawn FM (Explicit)]\n[by:]\n[offset:0]\n[00:00.00]腾讯音乐享有本翻译作品的著作权\n[00:02.59]//\n[00:05.19]//\n[00:07.79]我们要回到过去\n[00:09.71]我想看你为我努力\n[00:11.73]通过你大脑中的隧道解放你的思想\n[00:14.44]\n[00:15.59]我会给你倒上致幻的蘑菇茶\n[00:17.64]穿过永不平静的大海\n[00:19.63]让你释放自己 逃离现实\n[00:22.48]\n[00:23.57]这不能限制你\n[00:25.59]我需要突破\n[00:27.59]我只希望自己做出的选择都是对的\n[00:30.44]\n[00:31.53]这是如此与众不同\n[00:33.51]寻求认同\n[00:35.53]拼命地乞求\n[00:38.50]我问过你\n[00:39.15]\n[00:55.70]我要如何才能让你爱上我\n[00:58.52]\n[01:00.01]我要如何才能让你为我坠入爱河\n[01:02.86]\n[01:03.46]我要如何才能让你对我心生渴求\n[01:06.57]\n[01:07.71]让这份爱永远持续下去\n[01:10.74]\n[01:11.43]我要如何才能让你爱上我\n[01:14.43]//\n[01:15.76]我要如何才能让你为我坠入爱河\n[01:18.66]\n[01:19.41]我要如何才能让你对我心生渴求\n[01:22.68]//\n[01:23.67]让这份爱永远持续下去\n[01:27.35]我能够看到真实的你 女孩\n[01:29.34]你无需在我面前掩饰自己\n[01:31.10]忘记你父亲曾经说过的话吧\n[01:33.00]我会教会你如何绽放自己的光芒\n[01:35.07]你所忍受的那些事情\n[01:37.23]让你内心变得冰冷\n[01:38.95]但我能再次点燃你\n[01:40.86]就像火焰燃烧后的余烬\n[01:42.94]这不能限制你\n[01:44.92]我需要突破\n[01:46.89]我只希望自己做出的选择都是对的\n[01:49.80]\n[01:50.91]这是如此与众不同\n[01:52.85]寻求认同\n[01:54.94]绝望地乞求\n[01:57.89]我问过你\n[01:58.56]\n[01:59.18]我要如何才能让你爱上我\n[02:02.01]\n[02:03.40]我要如何才能让你为我坠入爱河\n[02:06.27]\n[02:07.03]我要如何才能让你对我心生渴求\n[02:10.17]\n[02:11.17]让这份爱永远持续下去\n[02:14.22]\n[02:14.90]我要如何才能让你爱上我\n[02:17.88]//\n[02:19.19]我要如何才能让你为我坠入爱河\n[02:22.16]\n[02:22.97]我要如何才能让你对我心生渴求\n[02:26.06]//\n[02:27.18]让这份爱永远持续下去"}}