{"result": 100, "data": {"retcode": 0, "code": 0, "subcode": 0, "lyric": "[ti:Life's A Mess (Explicit)]\n[ar:Juice WRLD/Halsey]\n[al:Life's A Mess (Explicit)]\n[by:]\n[offset:0]\n[00:00.00]Life's A Mess (Explicit) - Juice WRLD/Halsey\n[00:00.62]Lyrics by：Rex Kudo/Ashley Frangipane/Jarad Higgins/Ryan Vojesak\n[00:01.25]Composed by：Rex Kudo/Ashley Frangipane/Jarad Higgins/Ryan Vojesak\n[00:01.88]Juice WRLD：\n[00:03.24]Have you ever fallen head over heels for somebody\n[00:08.76]Not just somebody\n[00:11.10]No no\n[00:12.60]But she did again\n[00:13.39]Have you ever fallen head over heels for somebody\n[00:16.52]That made promises that give you the world\n[00:19.00]Um\n[00:19.53]I really hope they held you down\n[00:21.27]I really hope it was no lying 'cause when heart breaks\n[00:24.50]It feel like the world's gone\n[00:26.61]But if the love's real you'd feel your soul roar like a lion\n[00:30.08]And you'd finally let bygones be bygones\n[00:32.94]Don't throw in the towel I know it feels like you're the only one trying\n[00:36.81]You just gotta learn to live and love on\n[00:40.65]I belong with the one put on this earth for me\n[00:43.98]Everybody has their someone just gotta look and see\n[00:47.37]I'm screaming out \"Lord help me I've been lonely\"\n[00:50.21]That's when you accept me\n[00:52.07]Then you set me free\n[00:54.51]Uh sometimes life's a mess\n[00:57.90]Uh I get high when I'm upset\n[01:01.50]I remember when me and love didn't click\n[01:04.37]Searching for somethin' real then I found it\n[01:08.00]Uh-uh sometimes life's a mess\n[01:11.14]Yeah I get high when I'm upset\n[01:14.67]I remember when me and love ain't click\n[01:17.81]Looking for somethin' real then I found it\n[01:20.55]Can't put you f**king back well it's better now\n[01:24.04]Through the trials and tribulations I found my way out\n[01:26.74]Feel all of the good and bad vibrations all around\n[01:30.77]All around us they surround us\n[01:34.44]Was a lost cause with some lost love\n[01:37.76]It ain't my fault pain chose us then I found her\n[01:42.74]My whole world turned upside down uh\n[01:45.98]But for the better\n[01:47.86]I belong with the one put on this earth for me\n[01:51.01]Everybody has their someone just gotta look and see\n[01:54.49]I'm screaming out \"Lord help me I've been lonely\"\n[01:57.43]That's when you accept me\n[01:58.96]Then you set me free\n[02:00.90]Juice WRLD/Halsey：\n[02:01.46]Uh sometimes life's a mess\n[02:05.09]Uh I get high when I'm upset\n[02:08.36]I remember when me and love didn't click\n[02:11.61]Searching for somethin' real then I found it\n[02:15.16]Uh-uh sometimes life's a mess\n[02:18.24]Yeah I get high when I'm upset\n[02:21.87]I remember when me and love ain't click\n[02:24.94]Looking for somethin' real then I found it\n[02:28.16]Halsey：\n[02:29.02]Uh uh uh uh\n[02:32.20]Uh uh uh uh\n[02:35.61]Uh uh uh uh\n[02:38.85]Uh uh uh uh\n[02:41.91]Thank God I finally found you\n[02:45.02]You put the light in my eyes when I'm around you\n[02:48.16]I'm too flawed to hold you down but\n[02:51.76]Don't wanna be here alone\n[02:54.78]And I thank God I finally found you\n[02:58.47]I'll put the light in your eyes if I'm allowed to\n[03:01.79]I'm too flawed to hold you down but\n[03:05.18]Don't let me be here alone", "trans": "[ti:Life's A Mess (Explicit)]\n[ar:Juice WRLD/Halsey]\n[al:Life's A Mess (Explicit)]\n[by:]\n[offset:0]\n[00:00.00]腾讯享有本翻译作品的著作权\n[00:00.62]//\n[00:01.25]//\n[00:01.88]//\n[00:03.24]你是否曾为某人爱到死心塌地\n[00:08.76]不只是那一个\n[00:11.10]不 不\n[00:12.60]Rex 你又做到了\n[00:13.39]你是否曾为某人爱到死心塌地\n[00:16.52]某个许诺给你全世界的人\n[00:19.00]//\n[00:19.53]我真心希望有人已将你征服\n[00:21.27]我真心希望这一切不是谎言 因为当心支离破碎\n[00:24.50]感觉世界都崩塌瓦解\n[00:26.61]但如果遇上了真心的爱 你的灵魂会像狮子一样嘶吼\n[00:30.08]如果你最终决定放下过往\n[00:32.94]不要轻言放弃 我知道你觉得只有自己在不懈努力\n[00:36.81]你只是该学会怎样继续生活 继续爱\n[00:40.65]我属于那个为我来到这个世界的人\n[00:43.98]每个人都有自己的命中注定 只是需要自己去寻找\n[00:47.37]我放声呐喊 上帝 救救我 我被孤独缠上\n[00:50.21]等你接纳我的存在\n[00:52.07]我就能得到自由\n[00:54.51]生活有时会一团糟\n[00:57.90]失落沮丧时 却自甘堕落沉浸其中\n[01:01.50]我记得那时我合不上爱的节拍\n[01:04.37]一心寻觅真实的存在 终是得偿所愿\n[01:08.00]生活有时会一团糟\n[01:11.14]失落沮丧时 却自甘堕落沉浸其中\n[01:14.67]我记得那时我合不上爱的节拍\n[01:17.81]一心寻觅真实的存在 终是得偿所愿\n[01:20.55]尝尽苦楚 但现在苦尽甘来\n[01:24.04]翻越重重障碍 我踏上了那条康庄大道\n[01:26.74]感觉所有幸福和不幸的频率\n[01:30.77]将我们围绕 将我们围困其中\n[01:34.44]失败的爱情使我坠入了地狱\n[01:37.76]我没有犯错 是痛苦找上了我 直到遇见她\n[01:42.74]使我整个世界天翻地覆\n[01:45.98]为我铺开一片光明的未来\n[01:47.86]我属于那个为我来到这个世界的人\n[01:51.01]每个人都有自己的命中注定 只是需要自己去寻找\n[01:54.49]我放声呐喊 上帝 救救我 我被孤独缠上\n[01:57.43]等你接纳我的存在\n[01:58.96]我就能得到自由\n[02:00.90]//\n[02:01.46]生活有时会一团糟\n[02:05.09]失落沮丧时 却自甘堕落沉浸其中\n[02:08.36]我记得那时我合不上爱的节拍\n[02:11.61]一心寻觅真实的存在 终是得偿所愿\n[02:15.16]生活有时会一团糟\n[02:18.24]失落沮丧时 却自甘堕落沉浸其中\n[02:21.87]我记得那时我合不上爱的节拍\n[02:24.94]一心寻觅真实的存在 终是得偿所愿\n[02:28.16]//\n[02:29.02]//\n[02:32.20]//\n[02:35.61]//\n[02:38.85]//\n[02:41.91]感谢上帝 让我最后找到了你\n[02:45.02]当我来到你身边 你点亮了我眼中的光\n[02:48.16]我不够完美 没有资格拥有你 但是\n[02:51.76]我不想孤独一人\n[02:54.78]感谢上帝 让我最后找到了你\n[02:58.47]如果你愿意 我会点亮你眼中的光\n[03:01.79]我不够完美 没有资格拥有你 但是\n[03:05.18]不要让我孤独一人"}}