{"result": 100, "data": {"retcode": 0, "code": 0, "subcode": 0, "lyric": "[ti:Ruff Ryders&apos; Anthem]\n[ar:DMX]\n[al:The Definition Of X: Pick Of The Litter]\n[by:]\n[offset:0]\n[00:00.00]Ruff Ryders' Anthem (Explicit) - DMX\n[00:04.28]Lyrics by：Kasseem Dean/Earl Simmons\n[00:08.57]Composed by：Kasseem Dean/Earl Simmons\n[00:12.86]Something new\n[00:14.63]Stop drop shut &apos;em down open up shop\n[00:19.82]Oh no that&apos;s how Ruff Ryders roll\n[00:25.06]Stop drop shut &apos;em down open up shop\n[00:30.33]Oh no that&apos;s how Ruff Ryders roll\n[00:34.98]N***as wanna try n***as wanna lie\n[00:37.39]Then n***as wonder why n***as wanna die\n[00:40.28]All I know is pain all I feel is rain\n[00:42.81]How can I maintain with that s**t on my brain\n[00:45.44]I resort to violence my n***as move in silence\n[00:47.96]Like you don&apos;t know what our style is\n[00:49.29]New York n***as the wildest\n[00:50.85]My n***as is with it you want it come and get it\n[00:53.37]Took it then we split it you f**kin&apos; right we did it\n[00:56.03]What the f**k you gon&apos; do when we run up on you\n[00:58.64]F**kin&apos; with the wrong crew\n[00:59.97]Don&apos;t know what we&apos;re goin&apos; through\n[01:01.27]I&apos;ma have to show n***as how easily we blow n***as\n[01:03.72]When you find out there&apos;s some mo&apos; n***as\n[01:05.25]That&apos;s runnin&apos; with yo n***as\n[01:06.74]Nothin&apos; we can&apos;t handle break it up and dismantle\n[01:09.10]Light it up like a candle just &apos;cause I can&apos;t stand you\n[01:11.78]Put my s**t on tapes like you bustin&apos; grapes\n[01:14.47]Think you holdin&apos; weight\n[01:15.40]Then you haven&apos;t met the apes\n[01:17.85]Stop drop shut &apos;em down open up shop\n[01:22.98]Oh no that&apos;s how Ruff Ryders roll\n[01:28.28]Stop drop shut &apos;em down open up shop\n[01:33.59]Oh no that&apos;s how Ruff Ryders roll\n[01:37.99]Is y&apos;all n***as crazy\n[01:39.54]I&apos;ll bust you and be Swayze\n[01:40.64]Stop actin&apos; like a baby mind your business lady\n[01:43.51]Nosy people get it too when you see me spit at you\n[01:45.95]You know I&apos;m tryin&apos; to get rid of you yeah I know it&apos;s pitiful\n[01:48.76]That&apos;s how n***as get down\n[01:50.09]Watch my n***as spit rounds\n[01:51.23]Make y&apos;all n***as kiss ground just for talkin&apos; s**t clown\n[01:53.95]Oh you think it&apos;s funny\n[01:55.10]Then you don&apos;t know me money\n[01:56.62]It&apos;s about to get ugly f**k it dawg I&apos;m hungry\n[01:59.10]I guess you know what that mean\n[02:00.56]Come up off that green rob n***as on ravine\n[02:03.01]Don&apos;t make it a murder scene\n[02:04.51]Give a dog a bone leave a dog alone\n[02:07.15]Let a dog roam and he&apos;ll find his way home\n[02:09.82]Home of the brave my home is a cage\n[02:12.53]Ayo I&apos;ma slave till my home is a grave\n[02:15.17]I&apos;ma pull capers it&apos;s all about the papers\n[02:17.85]B***hes caught the vapors and now they wanna rape us\n[02:21.20]Stop drop shut &apos;em down open up shop\n[02:26.31]Oh no that&apos;s how Ruff Ryders roll\n[02:31.59]Stop drop shut &apos;em down open up shop\n[02:36.81]Oh no that&apos;s how Ruff Ryders roll\n[02:41.51]Look what you done started asked for it you got it\n[02:44.06]Had it shoulda shot it now you&apos;re dearly departed\n[02:46.55]Get at me dawg did I rip s**t\n[02:48.16]With this one here I flip s**t\n[02:49.40]N***as know when I kick s**t it&apos;s gon&apos; be some slick s**t\n[02:51.97]What was that look for when I walked in the door\n[02:54.63]Oh you thought you was raw\n[02:56.05]Boom not anymore\n[02:57.25]&apos;Cause now you on the floor wishin&apos; you never saw\n[02:59.75]Me walk through that door with that .44\n[03:02.57]Now it&apos;s time for bed two more to the head\n[03:05.18]Got the floor red yeah that n***a&apos;s dead\n[03:07.80]Another unsolved mystery it&apos;s goin&apos; down in history\n[03:10.40]N***as ain&apos;t never did s**t to me\n[03:11.93]B***h-a*s n***as can&apos;t get to me\n[03:13.17]Gots to make the move got a point to prove\n[03:15.73]Gotta make them groove got &apos;em all like &quot;Ooh&quot;\n[03:18.46]So to the next time you hear this n***a rhyme\n[03:21.02]Try to keep your mind on gettin&apos; p***y and crime\n[03:24.48]Stop drop shut &apos;em down open up shop\n[03:31.71]Talk is cheap motherf**ker", "trans": "[ti:Ruff Ryders' Anthem]\n[ar:DMX]\n[al:The Definition Of X: Pick Of The Litter]\n[by:]\n[offset:0]\n[00:00.00]//\n[00:04.28]//\n[00:08.57]//\n[00:12.86]//\n[00:14.63]阻止一切入侵 消灭一切敌人 锐不可当\n[00:19.82]不 饶舌奇兵 威震天下 \n[00:25.06]阻止一切入侵 消灭一切敌人 锐不可当\n[00:30.33]不 饶舌奇兵 威震天下 \n[00:34.98]兄弟们想要尝试 想要信口开河\n[00:37.39]兄弟们疑惑为什么有的人想要自寻死路\n[00:40.28]我只知道痛苦 我只想要腰缠万贯\n[00:42.81]有那么多烦心事 我为什么还可以逍遥自在 \n[00:45.44]我用武力解决一切 而我的兄弟在沉默中付出行动\n[00:47.96]好像你不知道我们的风格是什么似的\n[00:49.29]我们是纽约最狂野的乐队\n[00:50.85]我的兄弟们聪明伶俐 你也想和我们一样 过来加入我们吧\n[00:53.37]然后把你们撕得粉碎 去你们的 我们成功了 \n[00:56.03]我们威震天下 强过你们一百倍 你们到底想怎么样\n[00:58.64]去你们的团队\n[00:59.97]你们难道不知道我们到底有多厉害\n[01:01.27]我要让你们瞧瞧 我们是怎样不费吹灰之力就能把你们碾压\n[01:03.72]当你看到我们成群结队 团结一致\n[01:05.25]你们最好赶紧逃跑\n[01:06.74]没有什么是我们对付不了的 我们能瞬间让你们土崩瓦解\n[01:09.10]请点燃全场 因为我无法忍受你们\n[01:11.78]胆敢把我的唱片拿出来 随意玩弄 \n[01:14.47]也不想想你有几斤几两\n[01:15.40]竟敢和我抗衡\n[01:17.85]阻止一切入侵 消灭一切敌人 锐不可当\n[01:22.98]不 饶舌奇兵 威震天下 \n[01:28.28]阻止一切入侵 消灭一切敌人 锐不可当\n[01:33.59]不 饶舌奇兵 威震天下 \n[01:37.99]你们难道都疯了吗\n[01:39.54]我会像帕特里克斯威兹在电影中那样让你们粉身碎骨\n[01:40.64]女士 请别再像孩子那样 管好你自己的事情\n[01:43.51]你就像一个好管闲事的婆娘 我非常鄙视你 \n[01:45.95]你清楚我试图摆脱你的纠缠 我知道这让你感觉很可怜\n[01:48.76]这是兄弟们嘻哈的方式\n[01:50.09]看看我的兄弟们多么耀武扬威\n[01:51.23]让你们只能双膝跪地 亲吻我们脚下的土地 只为博得我们的欢乐 你们这群小丑\n[01:53.95]你竟然觉得这很好笑\n[01:55.10]你根本就不了解我到底有多富有\n[01:56.62]你们丑陋不堪 去你们的 我现在饥肠辘辘\n[01:59.10]我想你知道我在说些什么\n[02:00.56]我们想要大把的钞票 我们会大肆对你们掠夺\n[02:03.01]只是不要让它像案发现场\n[02:04.51]给他们一些好处 然后远离这群人\n[02:07.15]放他一条生路 他会自己找到回家的路\n[02:09.82]勇者之家 我的家似牢笼 \n[02:12.53]终身奴隶其中 \n[02:15.17]我大肆抢劫 只为掠夺钞票 \n[02:17.85]那些小妞见钱眼开 见到我们就想和我们缠绵\n[02:21.20]阻止一切入侵 消灭一切敌人 锐不可当\n[02:26.31]不 饶舌奇兵 威震天下 \n[02:31.59]阻止一切入侵 消灭一切敌人 锐不可当\n[02:36.81]不 饶舌奇兵 威震天下 \n[02:41.51]看看你都做了些什么\n[02:44.06]你咎由自取 活该得到惩罚 \n[02:46.55]还敢看着我 你这条小狗 看我不把你粉身碎骨\n[02:48.16]我在这儿腾空旋转 兄弟们知道当我旋转\n[02:49.40]兄弟们知道当我旋转 一定是帅翻天际\n[02:51.97]当我走进屋内 你们用什么样的眼神看着我\n[02:54.63]你觉得你很酷\n[02:56.05]砰的一声 你一点都不酷\n[02:57.25]因为此刻你已躺在地板上 希望你永远都不要再看我\n[02:59.75]我从那个门前走过 手里拿着一杆枪\n[03:02.57]此刻到了睡觉时间 再干掉两个人  \n[03:05.18]让鲜血染红地板 那个敌人已经被射死\n[03:07.80]又是一个未解之谜 这将被载入史册\n[03:10.40]兄弟们永远不会背叛我\n[03:11.93]那些混蛋敌人永远无法靠近我\n[03:13.17]想要采取行动抓到我  你们需要拿到证据\n[03:15.73]想要使音乐动感十足 使粉丝大声尖叫 \n[03:18.46]所以下次你再听到我们的旋律\n[03:21.02]纵情嗨翻全场\n[03:24.48]阻止一切入侵 消灭一切敌人 锐不可当\n[03:31.71]光说没有用"}}