{"result": 100, "data": {"retcode": 0, "code": 0, "subcode": 0, "lyric": "[ti:A BOY IS A GUN (Explicit)]\n[ar:Tyler, The Creator]\n[al:IGOR (Explicit)]\n[by:]\n[offset:0]\n[00:00.00]A BOY IS A GUN* (Explicit) - Tyler, The Creator\n[00:00.09]Lyrics by：Tyler Okonma/Bobby Dukes/Bobby Massey/Lester Allen McKenzie\n[00:00.19]Composed by：Tyler Okonma/Bobby Dukes/Bobby Massey/Lester Allen McKenzie\n[00:00.28]No don&apos;t shoot me down\n[00:02.86]Yeah\n[00:03.27]No don&apos;t shoot me down\n[00:05.62]Okay\n[00:06.25]No don&apos;t shoot me down\n[00:09.50]You so motherf**kin&apos; dangerous\n[00:10.73]You started with a mere hello\n[00:11.84]You so motherf**kin&apos; dangerous\n[00:13.72]You got me by my neck\n[00:14.88]A boy is a gun\n[00:15.57]That&apos;s why these other n***s lame to us\n[00:17.80]&apos;Cause all these other n***s lame as f**k\n[00:20.10]We show &apos;em no respect\n[00:22.28]You started with a mere hello\n[00:23.36]When the time&apos;s right yeah\n[00:25.18]When the time&apos;s right baby\n[00:26.34]When the time&apos;s right\n[00:27.02]A boy is a gun\n[00:28.07]Turn me up a little bit\n[00:30.48]No don&apos;t shoot me down\n[00:34.00]Take your hoodie off why you hide your face from me\n[00:36.76]Make your f**kin&apos; mind up I am sick of waitin&apos; patiently\n[00:39.68]How come you the best to me I know you the worst for me\n[00:42.85]Boy you sweet as sugar diabetic to the first degree\n[00:46.06]My spidey sensies got me on the fencies\n[00:48.80]Whole squad in Ginza travel bag by Balenci&apos;\n[00:52.10]Big dawg hittin&apos; big wheelies on the six speed\n[00:55.11]No don&apos;t shoot me down\n[00:58.45]You so motherf**kin&apos; dangerous\n[00:59.12]You started with a mere hello\n[01:00.65]You so motherf**kin&apos; dangerous\n[01:02.68]You got me by my neck\n[01:03.72]A boy is a gun\n[01:04.62]That&apos;s why these other n***s lame to us\n[01:06.78]&apos;Cause all these other n***s lame as f**k\n[01:08.96]They show &apos;em no respect\n[01:11.35]You started with a mere hello\n[01:12.21]When the time&apos;s right\n[01:12.99]Yeah\n[01:13.49]When the time&apos;s right baby\n[01:15.09]When the time&apos;s right\n[01:15.69]A boy is a gun\n[01:19.24]Look\n[01:19.67]No don&apos;t shoot me down\n[01:22.66]Oh you passive-aggressive\n[01:24.37]Oh you fakin&apos; you&apos;re mad\n[01:25.74]You started with a mere hello\n[01:26.75]Oh you wanna go home\n[01:27.65]Cool you better call you a cab\n[01:28.83]I ain&apos;t takin&apos; you home yeah I&apos;m brushin&apos; you off\n[01:31.89]&apos;Cause this parka is Comme you&apos;re my favorite garçon\n[01:34.75]Don&apos;t leave stay right here yeah I want you right near\n[01:37.55]You started with a mere hello\n[01:38.52]You invited me to breakfast why the f**k your ex here\n[01:40.82]Well let&apos;s see if you &apos;round the god around this time next year\n[01:43.85]No don&apos;t shoot me down\n[01:47.02]No don&apos;t shoot me down\n[01:48.88]F**ked up\n[01:49.86]No don&apos;t shoot me down\n[01:52.81]No don&apos;t shoot me down\n[01:56.19]You so motherf**kin&apos; dangerous\n[01:56.99]You started with a mere hello\n[01:57.97]You so motherf**kin&apos; dangerous\n[02:00.26]You got me by my neck\n[02:01.78]A boy is a gun\n[02:02.58]That&apos;s why these other n***s lame as f**k\n[02:04.90]Well I&apos;m here for you\n[02:08.92]You started with a mere hello\n[02:10.00]When the time&apos;s right yeah\n[02:11.85]When the time&apos;s right baby\n[02:13.09]When the time&apos;s right a boy is a gun\n[02:16.97]No don&apos;t shoot me down\n[02:21.16]You started with a mere hello\n[02:22.12]You&apos;re a gun &apos;cause I like you on my side at all times\n[02:28.79]You keep me safe\n[02:29.35]No don&apos;t shoot me down\n[02:32.06]You started with a mere hello\n[02:33.03]Wait wait depending on you know\n[02:35.53]All the time\n[02:37.22]You could be dangerous to me\n[02:40.42]Time time\n[02:41.45]Or anyone else\n[02:44.23]Look they be bringin&apos; us up\n[02:45.70]You started with a mere hello\n[02:46.67]Yeah like now and again\n[02:47.67]Give a f**k what they talkin&apos; &apos;bout I see you as a 10\n[02:51.06]I&apos;ma leave it at that I&apos;ma leave us as friends\n[02:54.25]&apos;Cause the irony is I don&apos;t wanna see you again\n[02:58.50]Stay the f**k away from me\n[03:01.53]Stay the f**k away from me\n[03:04.59]Stay the f**k away from me\n[03:06.15]I ain&apos;t gon&apos; repeat myself but stay the f**k away from me\n[03:10.09]You started with a mere hello\n[03:14.26]A boy is a gun\n[03:18.26]No don&apos;t shoot me down\n[03:22.34]You started with a mere hello\n[03:26.51]A boy is a gun", "trans": "[ti:A BOY IS A GUN (Explicit)]\n[ar:Tyler, The Creator]\n[al:IGOR (Explicit)]\n[by:]\n[offset:0]\n[00:00.00]//\n[00:00.09]//\n[00:00.18]//\n[00:00.28]不 不要射杀我\n[00:02.86]//\n[00:03.27]不 不要射杀我\n[00:05.62]//\n[00:06.25]不 不要射杀我\n[00:09.50]你是个危险分子\n[00:10.73]初遇时你只说了一句你好\n[00:11.84]你是个危险分子\n[00:13.72]你瞄准了我的脖子\n[00:14.88]男人的危险程度不亚于手枪\n[00:15.57]所以其他人对我们压根不构成威胁\n[00:17.80]因为其他人的实力都弱爆了\n[00:20.10]我们压根不把他们放在眼里\n[00:22.28]初遇时你只说了一句你好\n[00:23.36]就在时机正好的时候\n[00:25.18]就在时机正好的时候 宝贝\n[00:26.34]就在时机正好的时候\n[00:27.02]男人的危险程度不亚于手枪\n[00:28.07]把我的声音调大一点\n[00:30.48]不 不要射杀我\n[00:34.00]脱下你的连帽衫 你为何不敢正脸看我\n[00:36.76]赶紧下决定 我可没耐心等下去了\n[00:39.68]你在我眼里怎么可能是最优秀的 我看你是最差的吧\n[00:42.85]小子 你像个娘炮 我看你是得了一级糖尿病吧\n[00:46.06]我和蜘蛛侠一样对危险有特殊的感知能力 所以我总是处于警惕状态\n[00:48.80]整个团队的人一起来到日本Ginza购物中心 提着巴黎世家的旅行包\n[00:52.10]兄弟们开着豪车飞速驰骋\n[00:55.11]不 不要射杀我\n[00:58.45]你是个危险分子\n[00:59.12]初遇时你只说了一句你好\n[01:00.65]你是个危险分子\n[01:02.68]你瞄准了我的脖子\n[01:03.72]男人的危险程度不亚于手枪\n[01:04.62]所以其他人对我们压根不构成威胁\n[01:06.78]因为其他人的实力都弱爆了\n[01:08.96]我们压根不把他们放在眼里\n[01:11.35]初遇时你只说了一句你好\n[01:12.21]就在时机正好的时候\n[01:12.99]//\n[01:13.49]就在时机正好的时候 宝贝\n[01:15.09]就在时机正好的时候\n[01:15.69]男人的危险程度不亚于手枪\n[01:19.24]瞧\n[01:19.67]不 不要射杀我\n[01:22.66]你属于被动攻击型\n[01:24.37]你假装生气\n[01:25.74]初遇时你只说了一句你好\n[01:26.75]你想回家吗\n[01:27.65]行 你最好叫辆出租车\n[01:28.83]我不会送你回家 我才不会管你\n[01:31.89]这件皮大衣是Comme des Garçons的 你是我最喜欢的男孩\n[01:34.75]别走 留下来吧 我想要你待在我身边\n[01:37.55]初遇时你只说了一句你好\n[01:38.52]你邀请我一起吃早餐 可你的前任为何在这里\n[01:40.82]行 那就看你明年这个时候 还能不能找到我这种上帝般高贵的男人\n[01:43.85]不 不要射杀我\n[01:47.02]不 不要射杀我\n[01:48.88]简直乱来\n[01:49.86]不 不要射杀我\n[01:52.81]不 不要射杀我\n[01:56.19]你是个危险分子\n[01:56.99]初遇时你只说了一句你好\n[01:57.97]你是个危险分子\n[02:00.26]你瞄准了我的脖子\n[02:01.78]男人的危险程度不亚于手枪\n[02:02.58]所以其他人对我们压根不构成威胁\n[02:04.90]我为你而出现\n[02:08.92]初遇时你只说了一句你好\n[02:10.00]就在时机正好的时候\n[02:11.85]就在时机正好的时候 宝贝\n[02:13.09]就在时机正好的时候 男人的危险程度不亚于手枪\n[02:16.97]不 不要射杀我\n[02:21.16]初遇时你只说了一句你好\n[02:22.12]你像一把手枪 不论何时何地 我都想把你带在身边\n[02:28.79]你能保证我的人身安全\n[02:29.35]不 不要射杀我\n[02:32.06]初遇时你只说了一句你好\n[02:33.03]等一下 等一下 决定权在谁手里 \n[02:35.53]你一直都知道\n[02:37.22]你对我是个巨大的危胁\n[02:40.42]一直以为\n[02:41.45]对别人也一样\n[02:44.23]看 是他们把我们带大的\n[02:45.70]初遇时你只说了一句你好\n[02:46.67]仿佛似曾相识\n[02:47.67]从不在乎别人的意见 你在我眼里就是完美的\n[02:51.06]就这样吧 我们还是做朋友吧\n[02:54.25]令人觉得讽刺的是 我不想再见到你了\n[02:58.50]离我远点\n[03:01.53]离我远点\n[03:04.59]离我远点\n[03:06.15]我不想再重复了 离我远点\n[03:10.09]初遇时你只说了一句你好\n[03:14.26]男人的危险程度不亚于手枪\n[03:18.26]不 不要射杀我\n[03:22.34]初遇时你只说了一句你好\n[03:26.51]男人的危险程度不亚于手枪"}}